BlickUtils/__init__.py
BlickUtils/common.py
BlickUtils/core.py
BlickUtils/test.py
BlickUtils/utils_df.py
BlickUtils/utils_files.py
BlickUtils/utils_image.py
BlickUtils/utils_infra.py
BlickUtils/utils_process.py
blickutils-0.5.10.33.dist-info/licenses/LICENSE
blickutils-0.5.10.33.dist-info/METADATA
blickutils-0.5.10.33.dist-info/WHEEL
blickutils-0.5.10.33.dist-info/top_level.txt
blickutils-0.5.10.33.dist-info/RECORD
