Metadata-Version: 2.4
Name: BlickUtils
Version: 0.5.10.33
Summary: A collection of utility functions for Blick Technologies
Author-email: "Horst E." <horst@blicktek.com>
License: MIT
Classifier: Programming Language :: Python :: 3
Classifier: License :: OSI Approved :: MIT License
Classifier: Operating System :: OS Independent
Requires-Python: >=3.10
License-File: LICENSE
Requires-Dist: httpx>=0.1.0
Requires-Dist: tomli>=2.0.0
Dynamic: license-file
